PBFS
