Metadata-Version: 2.1
Name: PBFS
Version: 2.0.0
Summary: Performance Based Feature selection Technique: Prototype
Home-page: https://github.com/hongzhu6129/HidenFeatures
Author: Movin Fernandes, Prof. Hong Zhu
Author-email: movin.fernandes@hotmail.com, hzhu@brookes.ac.uk
Maintainer: Movin Fernandes
Maintainer-email: movin.fernandes@hotmail.com
License: MIT
Keywords: Feature selection,Machine learning,Feature engineering,Performance based,open source
License-File: LICENSE.txt
